[{"domain":"brief.academy","status":"available","attractiveness":124,"demand":19,"length":5,"created":"","expires":"","registrar":null,"sectors":"Business,Education,General,Law"},{"domain":"tenth.academy","status":"available","attractiveness":116,"demand":7,"length":5,"created":"","expires":"","registrar":null,"sectors":"Mathematics"},{"domain":"flat.academy","status":"available","attractiveness":116,"demand":24,"length":4,"created":"","expires":"","registrar":null,"sectors":"Construction,Real Estate"},{"domain":"zero.academy","status":"resell","attractiveness":112,"demand":49,"length":4,"created":"2024-09-28T17:00:17.000Z","expires":"2025-09-28T17:00:17.000Z","registrar":"Dynadot Inc","sectors":"Mathematics"},{"domain":"abstract.academy","status":"resell","attractiveness":108,"demand":29,"length":8,"created":"2017-05-10T17:53:16.000Z","expires":"2026-05-10T17:53:16.000Z","registrar":"GoDaddy.com, LLC","sectors":"Arts,Humanities,Science"},{"domain":"abiding.academy","status":"available","attractiveness":106,"demand":5,"length":7,"created":"","expires":"","registrar":null,"sectors":"General,Religion"},{"domain":"absent.academy","status":"available","attractiveness":102,"demand":8,"length":6,"created":"","expires":"","registrar":null,"sectors":"Business,Education,Technology"},{"domain":"remove.academy","status":"available","attractiveness":100,"demand":13,"length":6,"created":"","expires":"","registrar":null,"sectors":"Construction,Manufacturing,Technology"},{"domain":"sixth.academy","status":"available","attractiveness":100,"demand":8,"length":5,"created":"","expires":"","registrar":null,"sectors":"Mathematics"},{"domain":"eighth.academy","status":"available","attractiveness":100,"demand":6,"length":6,"created":"","expires":"","registrar":null,"sectors":"Mathematics"},{"domain":"abrupt.academy","status":"available","attractiveness":100,"demand":3,"length":6,"created":"","expires":"","registrar":null,"sectors":"Medicine,Science"},{"domain":"alamode.academy","status":"available","attractiveness":96,"demand":12,"length":9,"created":"","expires":"","registrar":null,"sectors":"Fashion"},{"domain":"forgiving.academy","status":"available","attractiveness":96,"demand":3,"length":9,"created":"","expires":"","registrar":null,"sectors":"Healthcare,Religion"},{"domain":"around.academy","status":"available","attractiveness":94,"demand":22,"length":6,"created":"","expires":"","registrar":null,"sectors":"Business,General,Media,Technology"},{"domain":"twentieth.academy","status":"available","attractiveness":92,"demand":3,"length":9,"created":"","expires":"","registrar":null,"sectors":"Mathematics"},{"domain":"nought.academy","status":"available","attractiveness":92,"demand":4,"length":6,"created":"","expires":"","registrar":null,"sectors":"Mathematics"},{"domain":"abroad.academy","status":"available","attractiveness":92,"demand":12,"length":6,"created":"","expires":"","registrar":null,"sectors":"Hospitality,Travel"},{"domain":"riveting.academy","status":"available","attractiveness":90,"demand":6,"length":8,"created":"","expires":"","registrar":null,"sectors":"Entertainment,Media,Technology"},{"domain":"gripping.academy","status":"available","attractiveness":90,"demand":3,"length":8,"created":"","expires":"","registrar":null,"sectors":"Entertainment,Media,Technology"},{"domain":"hundred.academy","status":"available","attractiveness":88,"demand":14,"length":7,"created":"","expires":"","registrar":null,"sectors":"Mathematics"},{"domain":"fifteen.academy","status":"available","attractiveness":88,"demand":13,"length":7,"created":"","expires":"","registrar":null,"sectors":"Mathematics"},{"domain":"twelve.academy","status":"available","attractiveness":88,"demand":18,"length":6,"created":"","expires":"","registrar":null,"sectors":"General,Mathematics"},{"domain":"sixteen.academy","status":"available","attractiveness":88,"demand":11,"length":7,"created":"","expires":"","registrar":null,"sectors":"Mathematics"},{"domain":"ace.academy","status":"available","attractiveness":88,"demand":34,"length":3,"created":"","expires":"","registrar":null,"sectors":"Sports"},{"domain":"xiv.academy","status":"available","attractiveness":86,"demand":12,"length":3,"created":"","expires":"","registrar":null,"sectors":"Mathematics"},{"domain":"engrossing.academy","status":"available","attractiveness":86,"demand":0,"length":10,"created":"","expires":"","registrar":null,"sectors":"Entertainment,Media,Technology"},{"domain":"xix.academy","status":"available","attractiveness":86,"demand":11,"length":3,"created":"","expires":"","registrar":null,"sectors":"Mathematics"},{"domain":"recondite.academy","status":"available","attractiveness":86,"demand":4,"length":9,"created":"","expires":"","registrar":null,"sectors":"Arts,Humanities,Science"},{"domain":"intent.academy","status":"expired","attractiveness":86,"demand":25,"length":6,"created":"2024-06-29T16:07:20.000Z","expires":"2025-06-29T16:07:20.000Z","registrar":"Porkbun LLC","sectors":"Business,Education,Technology"},{"domain":"nineteen.academy","status":"available","attractiveness":84,"demand":8,"length":8,"created":"","expires":"","registrar":null,"sectors":"Mathematics"},{"domain":"twentyone.academy","status":"available","attractiveness":84,"demand":13,"length":10,"created":"","expires":"","registrar":null,"sectors":"Mathematics"},{"domain":"seventeen.academy","status":"available","attractiveness":84,"demand":7,"length":9,"created":"","expires":"","registrar":null,"sectors":"Mathematics"},{"domain":"fourteen.academy","status":"available","attractiveness":84,"demand":8,"length":8,"created":"","expires":"","registrar":null,"sectors":"Mathematics"},{"domain":"thousand.academy","status":"available","attractiveness":84,"demand":8,"length":8,"created":"","expires":"","registrar":null,"sectors":"Mathematics"},{"domain":"twentytwo.academy","status":"available","attractiveness":84,"demand":11,"length":10,"created":"","expires":"","registrar":null,"sectors":"Mathematics"},{"domain":"absorbent.academy","status":"available","attractiveness":82,"demand":3,"length":9,"created":"","expires":"","registrar":null,"sectors":"Healthcare,Manufacturing,Retail"},{"domain":"dozen.academy","status":"available","attractiveness":82,"demand":10,"length":5,"created":"","expires":"","registrar":null,"sectors":"Mathematics"},{"domain":"cleansing.academy","status":"available","attractiveness":82,"demand":3,"length":9,"created":"","expires":"","registrar":null,"sectors":"Health and Fitness"},{"domain":"decade.academy","status":"available","attractiveness":82,"demand":10,"length":6,"created":"","expires":"","registrar":null,"sectors":"Mathematics"},{"domain":"abenaki.academy","status":"available","attractiveness":82,"demand":2,"length":7,"created":"","expires":"","registrar":null,"sectors":"Geography"},{"domain":"abroach.academy","status":"available","attractiveness":82,"demand":1,"length":7,"created":"","expires":"","registrar":null,"sectors":"Food and Beverage"},{"domain":"fivesome.academy","status":"available","attractiveness":82,"demand":1,"length":8,"created":"","expires":"","registrar":null,"sectors":"Sports"},{"domain":"abkhaz.academy","status":"available","attractiveness":82,"demand":1,"length":6,"created":"","expires":"","registrar":null,"sectors":"Geography"},{"domain":"enduring.academy","status":"available","attractiveness":82,"demand":9,"length":8,"created":"","expires":"","registrar":null,"sectors":"Health and Fitness,Religion"},{"domain":"abdominal.academy","status":"available","attractiveness":82,"demand":1,"length":9,"created":"","expires":"","registrar":null,"sectors":"Health and Fitness,Medicine"},{"domain":"absorbable.academy","status":"available","attractiveness":80,"demand":0,"length":10,"created":"","expires":"","registrar":null,"sectors":"Healthcare,Pharmaceuticals,Science"},{"domain":"first.academy","status":"resell","attractiveness":80,"demand":36,"length":5,"created":"2018-01-17T12:36:33.000Z","expires":"2026-01-17T12:36:33.000Z","registrar":"GoDaddy.com, LLC","sectors":"General,Mathematics"},{"domain":"able.academy","status":"resell","attractiveness":80,"demand":29,"length":4,"created":"2024-11-10T09:00:13.000Z","expires":"2025-11-10T09:00:13.000Z","registrar":"Sav.com, LLC","sectors":"Business,Education,General,Technology"},{"domain":"two.academy","status":"available","attractiveness":80,"demand":24,"length":3,"created":"","expires":"","registrar":null,"sectors":"Mathematics"},{"domain":"seventh.academy","status":"available","attractiveness":80,"demand":10,"length":7,"created":"","expires":"","registrar":null,"sectors":"Mathematics"},{"domain":"abundant.academy","status":"available","attractiveness":80,"demand":19,"length":8,"created":"","expires":"","registrar":null,"sectors":"Agriculture,Manufacturing,Retail"},{"domain":"nine.academy","status":"resell","attractiveness":80,"demand":24,"length":4,"created":"2023-05-08T16:43:48.000Z","expires":"2026-05-08T16:43:48.000Z","registrar":"NameCheap, Inc.","sectors":"General,Mathematics"},{"domain":"dorsal.academy","status":"available","attractiveness":80,"demand":6,"length":6,"created":"","expires":"","registrar":null,"sectors":"Medicine,Science"},{"domain":"twenty.academy","status":"available","attractiveness":80,"demand":12,"length":6,"created":"","expires":"","registrar":null,"sectors":"Mathematics"},{"domain":"forty.academy","status":"available","attractiveness":80,"demand":9,"length":5,"created":"","expires":"","registrar":null,"sectors":"Mathematics"},{"domain":"dormant.academy","status":"available","attractiveness":78,"demand":4,"length":7,"created":"","expires":"","registrar":null,"sectors":"Medicine,Science"},{"domain":"low.academy","status":"available","attractiveness":78,"demand":20,"length":3,"created":"","expires":"","registrar":null,"sectors":"Business,Finance"},{"domain":"twentysix.academy","status":"available","attractiveness":78,"demand":8,"length":10,"created":"","expires":"","registrar":null,"sectors":"Mathematics"},{"domain":"abkhasian.academy","status":"available","attractiveness":78,"demand":1,"length":9,"created":"","expires":"","registrar":null,"sectors":"Geography"},{"domain":"abounding.academy","status":"available","attractiveness":78,"demand":2,"length":9,"created":"","expires":"","registrar":null,"sectors":"Agriculture"},{"domain":"absorptive.academy","status":"available","attractiveness":78,"demand":1,"length":10,"created":"","expires":"","registrar":null,"sectors":"Healthcare,Manufacturing,Retail"},{"domain":"sixtynine.academy","status":"available","attractiveness":78,"demand":8,"length":10,"created":"","expires":"","registrar":null,"sectors":"Mathematics"},{"domain":"abkhazian.academy","status":"available","attractiveness":78,"demand":1,"length":9,"created":"","expires":"","registrar":null,"sectors":"Geography"},{"domain":"honestly.academy","status":"available","attractiveness":78,"demand":9,"length":8,"created":"","expires":"","registrar":null,"sectors":"Business,Law"},{"domain":"hundredth.academy","status":"available","attractiveness":76,"demand":1,"length":9,"created":"","expires":"","registrar":null,"sectors":"Mathematics"},{"domain":"eighteen.academy","status":"available","attractiveness":76,"demand":7,"length":8,"created":"","expires":"","registrar":null,"sectors":"Mathematics"},{"domain":"threed.academy","status":"available","attractiveness":76,"demand":7,"length":7,"created":"","expires":"","registrar":null,"sectors":"Technology"},{"domain":"firstrate.academy","status":"available","attractiveness":76,"demand":6,"length":10,"created":"","expires":"","registrar":null,"sectors":"Business"},{"domain":"fourteenth.academy","status":"available","attractiveness":76,"demand":1,"length":10,"created":"","expires":"","registrar":null,"sectors":"Mathematics"},{"domain":"thousandth.academy","status":"available","attractiveness":76,"demand":1,"length":10,"created":"","expires":"","registrar":null,"sectors":"Mathematics"},{"domain":"nineteenth.academy","status":"available","attractiveness":76,"demand":3,"length":10,"created":"","expires":"","registrar":null,"sectors":"Mathematics"},{"domain":"thirteenth.academy","status":"available","attractiveness":76,"demand":4,"length":10,"created":"","expires":"","registrar":null,"sectors":"Mathematics"},{"domain":"fifteenth.academy","status":"available","attractiveness":76,"demand":2,"length":9,"created":"","expires":"","registrar":null,"sectors":"Mathematics"},{"domain":"abrasive.academy","status":"available","attractiveness":76,"demand":6,"length":8,"created":"","expires":"","registrar":null,"sectors":"Construction,Manufacturing"},{"domain":"single.academy","status":"available","attractiveness":74,"demand":19,"length":6,"created":"","expires":"","registrar":null,"sectors":"Sports"},{"domain":"cleared.academy","status":"available","attractiveness":74,"demand":7,"length":7,"created":"","expires":"","registrar":null,"sectors":"Healthcare,Law,Transportation"},{"domain":"aberrant.academy","status":"available","attractiveness":74,"demand":6,"length":8,"created":"","expires":"","registrar":null,"sectors":"Medicine,Science"},{"domain":"ternary.academy","status":"resell","attractiveness":72,"demand":7,"length":7,"created":"2024-08-12T09:03:17.000Z","expires":"2026-08-12T09:03:17.000Z","registrar":"Sav.com, LLC","sectors":"Mathematics"},{"domain":"abreast.academy","status":"available","attractiveness":72,"demand":2,"length":7,"created":"","expires":"","registrar":null,"sectors":"Business,Technology"},{"domain":"eightieth.academy","status":"available","attractiveness":72,"demand":1,"length":9,"created":"","expires":"","registrar":null,"sectors":"Mathematics"},{"domain":"liv.academy","status":"resell","attractiveness":72,"demand":27,"length":3,"created":"2025-07-29T17:05:16.000Z","expires":"2026-07-29T17:05:16.000Z","registrar":"Spaceship, Inc.","sectors":"Mathematics"},{"domain":"trey.academy","status":"available","attractiveness":72,"demand":14,"length":4,"created":"","expires":"","registrar":null,"sectors":"Sports"},{"domain":"ablaze.academy","status":"available","attractiveness":72,"demand":6,"length":6,"created":"","expires":"","registrar":null,"sectors":"Entertainment"},{"domain":"seventieth.academy","status":"available","attractiveness":72,"demand":1,"length":10,"created":"","expires":"","registrar":null,"sectors":"Mathematics"},{"domain":"absorbed.academy","status":"available","attractiveness":72,"demand":2,"length":8,"created":"","expires":"","registrar":null,"sectors":"Entertainment,Media,Technology"},{"domain":"trinity.academy","status":"available","attractiveness":72,"demand":18,"length":7,"created":"","expires":"","registrar":null,"sectors":"Religion"},{"domain":"engrossed.academy","status":"available","attractiveness":72,"demand":1,"length":9,"created":"","expires":"","registrar":null,"sectors":"Entertainment,Media,Technology"},{"domain":"sixtieth.academy","status":"available","attractiveness":72,"demand":1,"length":8,"created":"","expires":"","registrar":null,"sectors":"Mathematics"},{"domain":"ninetieth.academy","status":"available","attractiveness":72,"demand":1,"length":9,"created":"","expires":"","registrar":null,"sectors":"Mathematics"},{"domain":"absolutist.academy","status":"available","attractiveness":72,"demand":1,"length":10,"created":"","expires":"","registrar":null,"sectors":"Humanities,Law,Politics"},{"domain":"abloom.academy","status":"available","attractiveness":72,"demand":5,"length":6,"created":"","expires":"","registrar":null,"sectors":"Agriculture"},{"domain":"abulic.academy","status":"available","attractiveness":70,"demand":1,"length":6,"created":"","expires":"","registrar":null,"sectors":"Medicine"},{"domain":"absorbing.academy","status":"available","attractiveness":70,"demand":3,"length":9,"created":"","expires":"","registrar":null,"sectors":"Entertainment,Media,Technology"},{"domain":"tiptop.academy","status":"resell","attractiveness":70,"demand":24,"length":6,"created":"2021-07-22T00:09:15.000Z","expires":"2026-07-22T00:09:15.000Z","registrar":"NameCheap, Inc.","sectors":"Fashion"},{"domain":"abradant.academy","status":"available","attractiveness":70,"demand":1,"length":8,"created":"","expires":"","registrar":null,"sectors":"Construction,Manufacturing"},{"domain":"abnaki.academy","status":"available","attractiveness":68,"demand":1,"length":6,"created":"","expires":"","registrar":null,"sectors":"Geography"},{"domain":"fortieth.academy","status":"available","attractiveness":68,"demand":0,"length":8,"created":"","expires":"","registrar":null,"sectors":"Mathematics"},{"domain":"abducent.academy","status":"available","attractiveness":68,"demand":0,"length":8,"created":"","expires":"","registrar":null,"sectors":"Medicine"},{"domain":"vindicated.academy","status":"available","attractiveness":68,"demand":2,"length":10,"created":"","expires":"","registrar":null,"sectors":"Humanities,Law,Politics"},{"domain":"ablative.academy","status":"available","attractiveness":68,"demand":3,"length":8,"created":"","expires":"","registrar":null,"sectors":"Science"},{"domain":"fiftieth.academy","status":"available","attractiveness":68,"demand":0,"length":8,"created":"","expires":"","registrar":null,"sectors":"Mathematics"},{"domain":"sevener.academy","status":"available","attractiveness":68,"demand":1,"length":7,"created":"","expires":"","registrar":null,"sectors":"Mathematics"},{"domain":"abkhas.academy","status":"available","attractiveness":68,"demand":0,"length":6,"created":"","expires":"","registrar":null,"sectors":"Geography"},{"domain":"threesome.academy","status":"available","attractiveness":68,"demand":5,"length":9,"created":"","expires":"","registrar":null,"sectors":"Entertainment"},{"domain":"septenary.academy","status":"available","attractiveness":68,"demand":1,"length":9,"created":"","expires":"","registrar":null,"sectors":"Mathematics"},{"domain":"foursome.academy","status":"available","attractiveness":68,"demand":4,"length":8,"created":"","expires":"","registrar":null,"sectors":"Sports"},{"domain":"ennead.academy","status":"available","attractiveness":68,"demand":5,"length":6,"created":"","expires":"","registrar":null,"sectors":"Mathematics"},{"domain":"thirtieth.academy","status":"available","attractiveness":68,"demand":1,"length":9,"created":"","expires":"","registrar":null,"sectors":"Mathematics"},{"domain":"aberdonian.academy","status":"available","attractiveness":68,"demand":1,"length":10,"created":"","expires":"","registrar":null,"sectors":"Geography"},{"domain":"aroused.academy","status":"available","attractiveness":68,"demand":3,"length":7,"created":"","expires":"","registrar":null,"sectors":"Entertainment,Health and Fitness"},{"domain":"octonary.academy","status":"available","attractiveness":68,"demand":1,"length":8,"created":"","expires":"","registrar":null,"sectors":"Mathematics"},{"domain":"xxi.academy","status":"available","attractiveness":66,"demand":10,"length":3,"created":"","expires":"","registrar":null,"sectors":"Mathematics"},{"domain":"five.academy","status":"available","attractiveness":66,"demand":26,"length":4,"created":"","expires":"","registrar":null,"sectors":"Mathematics"},{"domain":"abstinent.academy","status":"available","attractiveness":66,"demand":1,"length":9,"created":"","expires":"","registrar":null,"sectors":"Health and Fitness,Religion"},{"domain":"exonerated.academy","status":"available","attractiveness":66,"demand":2,"length":10,"created":"","expires":"","registrar":null,"sectors":"Humanities,Law,Politics"},{"domain":"xviii.academy","status":"available","attractiveness":66,"demand":5,"length":5,"created":"","expires":"","registrar":null,"sectors":"Mathematics"},{"domain":"tenner.academy","status":"available","attractiveness":66,"demand":5,"length":6,"created":"","expires":"","registrar":null,"sectors":"Finance"},{"domain":"fifty.academy","status":"available","attractiveness":66,"demand":12,"length":5,"created":"","expires":"","registrar":null,"sectors":"Mathematics"},{"domain":"xii.academy","status":"available","attractiveness":66,"demand":10,"length":3,"created":"","expires":"","registrar":null,"sectors":"Mathematics"},{"domain":"ninety.academy","status":"available","attractiveness":66,"demand":11,"length":6,"created":"","expires":"","registrar":null,"sectors":"Mathematics"},{"domain":"six.academy","status":"available","attractiveness":66,"demand":26,"length":3,"created":"","expires":"","registrar":null,"sectors":"Mathematics"},{"domain":"xiii.academy","status":"available","attractiveness":66,"demand":9,"length":4,"created":"","expires":"","registrar":null,"sectors":"Mathematics"},{"domain":"thirty.academy","status":"available","attractiveness":66,"demand":8,"length":6,"created":"","expires":"","registrar":null,"sectors":"Mathematics"},{"domain":"latest.academy","status":"available","attractiveness":66,"demand":18,"length":6,"created":"","expires":"","registrar":null,"sectors":"Technology"},{"domain":"sextet.academy","status":"available","attractiveness":66,"demand":1,"length":6,"created":"","expires":"","registrar":null,"sectors":"Entertainment"},{"domain":"xvii.academy","status":"available","attractiveness":66,"demand":5,"length":4,"created":"","expires":"","registrar":null,"sectors":"Mathematics"},{"domain":"clv.academy","status":"available","attractiveness":66,"demand":10,"length":3,"created":"","expires":"","registrar":null,"sectors":"Mathematics"},{"domain":"onec.academy","status":"available","attractiveness":66,"demand":6,"length":5,"created":"","expires":"","registrar":null,"sectors":"Mathematics"},{"domain":"xvi.academy","status":"available","attractiveness":66,"demand":5,"length":3,"created":"","expires":"","registrar":null,"sectors":"Mathematics"},{"domain":"modish.academy","status":"available","attractiveness":66,"demand":5,"length":6,"created":"","expires":"","registrar":null,"sectors":"Fashion"},{"domain":"xxvi.academy","status":"available","attractiveness":66,"demand":3,"length":4,"created":"","expires":"","registrar":null,"sectors":"Mathematics"},{"domain":"xxii.academy","status":"available","attractiveness":66,"demand":6,"length":4,"created":"","expires":"","registrar":null,"sectors":"Mathematics"},{"domain":"deuce.academy","status":"available","attractiveness":66,"demand":9,"length":5,"created":"","expires":"","registrar":null,"sectors":"Sports"},{"domain":"absolved.academy","status":"available","attractiveness":64,"demand":1,"length":8,"created":"","expires":"","registrar":null,"sectors":"Humanities,Law,Religion"},{"domain":"aflame.academy","status":"available","attractiveness":64,"demand":3,"length":6,"created":"","expires":"","registrar":null,"sectors":"Entertainment"},{"domain":"nondrinker.academy","status":"available","attractiveness":64,"demand":1,"length":10,"created":"","expires":"","registrar":null,"sectors":"Health and Fitness,Religion"},{"domain":"aufait.academy","status":"available","attractiveness":62,"demand":3,"length":7,"created":"","expires":"","registrar":null,"sectors":"Fashion,Media"},{"domain":"troika.academy","status":"available","attractiveness":62,"demand":8,"length":6,"created":"","expires":"","registrar":null,"sectors":"Politics"},{"domain":"wrapped.academy","status":"available","attractiveness":62,"demand":13,"length":7,"created":"","expires":"","registrar":null,"sectors":"Fashion,Hospitality,Retail"},{"domain":"sixteenth.academy","status":"available","attractiveness":62,"demand":1,"length":9,"created":"","expires":"","registrar":null,"sectors":"Mathematics"},{"domain":"aborigine.academy","status":"available","attractiveness":62,"demand":1,"length":9,"created":"","expires":"","registrar":null,"sectors":"Humanities"},{"domain":"longdozen.academy","status":"available","attractiveness":62,"demand":2,"length":10,"created":"","expires":"","registrar":null,"sectors":"Mathematics"},{"domain":"eighteenth.academy","status":"available","attractiveness":62,"demand":1,"length":10,"created":"","expires":"","registrar":null,"sectors":"Mathematics"},{"domain":"twodozen.academy","status":"available","attractiveness":62,"demand":1,"length":9,"created":"","expires":"","registrar":null,"sectors":"Mathematics"},{"domain":"roughly.academy","status":"available","attractiveness":62,"demand":3,"length":7,"created":"","expires":"","registrar":null,"sectors":"Business,Media,Technology"},{"domain":"exculpated.academy","status":"available","attractiveness":62,"demand":1,"length":10,"created":"","expires":"","registrar":null,"sectors":"Humanities,Law,Politics"},{"domain":"orso.academy","status":"available","attractiveness":62,"demand":9,"length":5,"created":"","expires":"","registrar":null,"sectors":"Business,Media,Technology"},{"domain":"quartet.academy","status":"available","attractiveness":62,"demand":7,"length":7,"created":"","expires":"","registrar":null,"sectors":"Arts,Entertainment"},{"domain":"fortyfour.academy","status":"available","attractiveness":62,"demand":6,"length":10,"created":"","expires":"","registrar":null,"sectors":"Mathematics"},{"domain":"chiliad.academy","status":"available","attractiveness":62,"demand":2,"length":7,"created":"","expires":"","registrar":null,"sectors":"Mathematics"},{"domain":"eleventh.academy","status":"available","attractiveness":62,"demand":5,"length":8,"created":"","expires":"","registrar":null,"sectors":"Mathematics"},{"domain":"cxx.academy","status":"available","attractiveness":60,"demand":10,"length":3,"created":"","expires":"","registrar":null,"sectors":"Mathematics"},{"domain":"cxl.academy","status":"available","attractiveness":60,"demand":7,"length":3,"created":"","expires":"","registrar":null,"sectors":"Mathematics"},{"domain":"cxxx.academy","status":"available","attractiveness":60,"demand":4,"length":4,"created":"","expires":"","registrar":null,"sectors":"Mathematics"},{"domain":"clx.academy","status":"available","attractiveness":60,"demand":10,"length":3,"created":"","expires":"","registrar":null,"sectors":"Mathematics"},{"domain":"clxv.academy","status":"available","attractiveness":60,"demand":1,"length":4,"created":"","expires":"","registrar":null,"sectors":"Mathematics"},{"domain":"clxx.academy","status":"available","attractiveness":60,"demand":3,"length":4,"created":"","expires":"","registrar":null,"sectors":"Mathematics"},{"domain":"paunchy.academy","status":"available","attractiveness":60,"demand":0,"length":7,"created":"","expires":"","registrar":null,"sectors":"Health and Fitness,Medicine"},{"domain":"abstainer.academy","status":"available","attractiveness":60,"demand":0,"length":9,"created":"","expires":"","registrar":null,"sectors":"Health and Fitness,Religion"},{"domain":"cxxxv.academy","status":"available","attractiveness":60,"demand":2,"length":5,"created":"","expires":"","registrar":null,"sectors":"Mathematics"},{"domain":"eightysix.academy","status":"available","attractiveness":60,"demand":7,"length":10,"created":"","expires":"","registrar":null,"sectors":"Mathematics"},{"domain":"cxxv.academy","status":"available","attractiveness":60,"demand":1,"length":4,"created":"","expires":"","registrar":null,"sectors":"Mathematics"},{"domain":"xcl.academy","status":"available","attractiveness":60,"demand":5,"length":3,"created":"","expires":"","registrar":null,"sectors":"Mathematics"},{"domain":"cxv.academy","status":"available","attractiveness":60,"demand":4,"length":3,"created":"","expires":"","registrar":null,"sectors":"Mathematics"},{"domain":"clxxv.academy","status":"available","attractiveness":60,"demand":1,"length":5,"created":"","expires":"","registrar":null,"sectors":"Mathematics"},{"domain":"abashed.academy","status":"available","attractiveness":60,"demand":1,"length":7,"created":"","expires":"","registrar":null,"sectors":"Humanities"},{"domain":"aboveboard.academy","status":"available","attractiveness":60,"demand":5,"length":10,"created":"","expires":"","registrar":null,"sectors":"Business,Law"},{"domain":"clxxx.academy","status":"available","attractiveness":60,"demand":1,"length":5,"created":"","expires":"","registrar":null,"sectors":"Mathematics"},{"domain":"sixty.academy","status":"available","attractiveness":60,"demand":13,"length":5,"created":"","expires":"","registrar":null,"sectors":"Mathematics"},{"domain":"cxlv.academy","status":"available","attractiveness":60,"demand":2,"length":4,"created":"","expires":"","registrar":null,"sectors":"Mathematics"},{"domain":"abstemious.academy","status":"available","attractiveness":60,"demand":0,"length":10,"created":"","expires":"","registrar":null,"sectors":"Food and Beverage,Health and Fitness,Hospitality"},{"domain":"thou.academy","status":"available","attractiveness":60,"demand":7,"length":4,"created":"","expires":"","registrar":null,"sectors":"Mathematics"},{"domain":"tertiary.academy","status":"available","attractiveness":60,"demand":4,"length":8,"created":"","expires":"","registrar":null,"sectors":"Education"},{"domain":"super.academy","status":"resell","attractiveness":58,"demand":47,"length":5,"created":"2022-04-23T13:15:00.000Z","expires":"2026-04-23T13:15:00.000Z","registrar":"Spaceship, Inc.","sectors":"Business"},{"domain":"tetrad.academy","status":"available","attractiveness":58,"demand":5,"length":6,"created":"","expires":"","registrar":null,"sectors":"Mathematics"},{"domain":"closeto.academy","status":"available","attractiveness":58,"demand":3,"length":8,"created":"","expires":"","registrar":null,"sectors":"Business,Media,Technology"},{"domain":"centesimal.academy","status":"available","attractiveness":58,"demand":1,"length":10,"created":"","expires":"","registrar":null,"sectors":"Mathematics"},{"domain":"lxxx.academy","status":"available","attractiveness":58,"demand":2,"length":4,"created":"","expires":"","registrar":null,"sectors":"Mathematics"},{"domain":"abridged.academy","status":"available","attractiveness":58,"demand":4,"length":8,"created":"","expires":"","registrar":null,"sectors":"Media"},{"domain":"niner.academy","status":"available","attractiveness":58,"demand":5,"length":5,"created":"","expires":"","registrar":null,"sectors":"Mathematics"},{"domain":"aucourant.academy","status":"available","attractiveness":58,"demand":3,"length":10,"created":"","expires":"","registrar":null,"sectors":"Fashion,Media"},{"domain":"alacarte.academy","status":"available","attractiveness":58,"demand":11,"length":10,"created":"","expires":"","registrar":null,"sectors":"Food and Beverage"},{"domain":"seventy.academy","status":"available","attractiveness":58,"demand":7,"length":7,"created":"","expires":"","registrar":null,"sectors":"Mathematics"},{"domain":"fourscore.academy","status":"available","attractiveness":58,"demand":4,"length":9,"created":"","expires":"","registrar":null,"sectors":"Mathematics"},{"domain":"justabout.academy","status":"available","attractiveness":58,"demand":3,"length":10,"created":"","expires":"","registrar":null,"sectors":"Business,Media,Technology"},{"domain":"heptad.academy","status":"available","attractiveness":58,"demand":1,"length":6,"created":"","expires":"","registrar":null,"sectors":"Mathematics"},{"domain":"abuzz.academy","status":"available","attractiveness":58,"demand":5,"length":5,"created":"","expires":"","registrar":null,"sectors":"Entertainment,Media,Technology"},{"domain":"cypher.academy","status":"available","attractiveness":58,"demand":29,"length":6,"created":"","expires":"","registrar":null,"sectors":"Mathematics"},{"domain":"hexad.academy","status":"available","attractiveness":58,"demand":4,"length":5,"created":"","expires":"","registrar":null,"sectors":"Mathematics"},{"domain":"pentad.academy","status":"available","attractiveness":58,"demand":2,"length":6,"created":"","expires":"","registrar":null,"sectors":"Mathematics"},{"domain":"octad.academy","status":"available","attractiveness":58,"demand":5,"length":5,"created":"","expires":"","registrar":null,"sectors":"Mathematics"},{"domain":"sixer.academy","status":"available","attractiveness":58,"demand":5,"length":5,"created":"","expires":"","registrar":null,"sectors":"Sports"},{"domain":"fourth.academy","status":"available","attractiveness":58,"demand":13,"length":6,"created":"","expires":"","registrar":null,"sectors":"Mathematics"},{"domain":"eighter.academy","status":"available","attractiveness":58,"demand":2,"length":7,"created":"","expires":"","registrar":null,"sectors":"Mathematics"},{"domain":"sixtyone.academy","status":"available","attractiveness":58,"demand":3,"length":9,"created":"","expires":"","registrar":null,"sectors":"Mathematics"},{"domain":"sextuplet.academy","status":"available","attractiveness":58,"demand":1,"length":9,"created":"","expires":"","registrar":null,"sectors":"Healthcare"},{"domain":"enwrapped.academy","status":"available","attractiveness":58,"demand":0,"length":9,"created":"","expires":"","registrar":null,"sectors":"Entertainment,Fashion,Media"},{"domain":"twelfth.academy","status":"available","attractiveness":58,"demand":2,"length":7,"created":"","expires":"","registrar":null,"sectors":"Mathematics"},{"domain":"xli.academy","status":"available","attractiveness":56,"demand":5,"length":3,"created":"","expires":"","registrar":null,"sectors":"Mathematics"},{"domain":"fortysix.academy","status":"available","attractiveness":56,"demand":3,"length":9,"created":"","expires":"","registrar":null,"sectors":"Mathematics"},{"domain":"xxxii.academy","status":"available","attractiveness":56,"demand":1,"length":5,"created":"","expires":"","registrar":null,"sectors":"Mathematics"},{"domain":"fiftyone.academy","status":"available","attractiveness":56,"demand":7,"length":9,"created":"","expires":"","registrar":null,"sectors":"Mathematics"},{"domain":"thirtysix.academy","status":"available","attractiveness":56,"demand":5,"length":10,"created":"","expires":"","registrar":null,"sectors":"Mathematics"},{"domain":"liii.academy","status":"available","attractiveness":56,"demand":4,"length":4,"created":"","expires":"","registrar":null,"sectors":"Mathematics"},{"domain":"abeyant.academy","status":"available","attractiveness":56,"demand":1,"length":7,"created":"","expires":"","registrar":null,"sectors":"Business,Law"},{"domain":"abdominous.academy","status":"available","attractiveness":56,"demand":0,"length":10,"created":"","expires":"","registrar":null,"sectors":"Health and Fitness,Medicine"},{"domain":"xliii.academy","status":"available","attractiveness":56,"demand":1,"length":5,"created":"","expires":"","registrar":null,"sectors":"Mathematics"},{"domain":"xxviii.academy","status":"available","attractiveness":56,"demand":1,"length":6,"created":"","expires":"","registrar":null,"sectors":"Mathematics"},{"domain":"lii.academy","status":"available","attractiveness":56,"demand":7,"length":3,"created":"","expires":"","registrar":null,"sectors":"Mathematics"},{"domain":"halfdozen.academy","status":"available","attractiveness":56,"demand":1,"length":10,"created":"","expires":"","registrar":null,"sectors":"Mathematics"},{"domain":"fortyone.academy","status":"available","attractiveness":56,"demand":4,"length":9,"created":"","expires":"","registrar":null,"sectors":"Mathematics"},{"domain":"xxxvi.academy","status":"available","attractiveness":56,"demand":1,"length":5,"created":"","expires":"","registrar":null,"sectors":"Mathematics"},{"domain":"lvii.academy","status":"available","attractiveness":56,"demand":1,"length":4,"created":"","expires":"","registrar":null,"sectors":"Mathematics"},{"domain":"thirtyone.academy","status":"available","attractiveness":56,"demand":5,"length":10,"created":"","expires":"","registrar":null,"sectors":"Mathematics"},{"domain":"xxxiv.academy","status":"available","attractiveness":56,"demand":1,"length":5,"created":"","expires":"","registrar":null,"sectors":"Mathematics"},{"domain":"xxix.academy","status":"available","attractiveness":56,"demand":4,"length":4,"created":"","expires":"","registrar":null,"sectors":"Mathematics"},{"domain":"xlii.academy","status":"available","attractiveness":56,"demand":5,"length":4,"created":"","expires":"","registrar":null,"sectors":"Mathematics"},{"domain":"fiftyfour.academy","status":"available","attractiveness":56,"demand":3,"length":10,"created":"","expires":"","registrar":null,"sectors":"Mathematics"},{"domain":"xxiv.academy","status":"available","attractiveness":56,"demand":5,"length":4,"created":"","expires":"","registrar":null,"sectors":"Mathematics"},{"domain":"xlviii.academy","status":"available","attractiveness":56,"demand":1,"length":6,"created":"","expires":"","registrar":null,"sectors":"Mathematics"},{"domain":"ilx.academy","status":"available","attractiveness":56,"demand":5,"length":3,"created":"","expires":"","registrar":null,"sectors":"Mathematics"},{"domain":"thirtytwo.academy","status":"available","attractiveness":56,"demand":5,"length":10,"created":"","expires":"","registrar":null,"sectors":"Mathematics"},{"domain":"xxxviii.academy","status":"available","attractiveness":56,"demand":1,"length":7,"created":"","expires":"","registrar":null,"sectors":"Mathematics"},{"domain":"fiftysix.academy","status":"available","attractiveness":56,"demand":4,"length":9,"created":"","expires":"","registrar":null,"sectors":"Mathematics"},{"domain":"xxiii.academy","status":"available","attractiveness":56,"demand":5,"length":5,"created":"","expires":"","registrar":null,"sectors":"Mathematics"},{"domain":"fiftytwo.academy","status":"available","attractiveness":56,"demand":6,"length":9,"created":"","expires":"","registrar":null,"sectors":"Mathematics"},{"domain":"xxxv.academy","status":"available","attractiveness":56,"demand":4,"length":4,"created":"","expires":"","registrar":null,"sectors":"Mathematics"},{"domain":"potbellied.academy","status":"available","attractiveness":56,"demand":0,"length":10,"created":"","expires":"","registrar":null,"sectors":"Health and Fitness,Medicine"},{"domain":"fortytwo.academy","status":"available","attractiveness":56,"demand":17,"length":9,"created":"","expires":"","registrar":null,"sectors":"Mathematics"},{"domain":"lviii.academy","status":"available","attractiveness":56,"demand":1,"length":5,"created":"","expires":"","registrar":null,"sectors":"Mathematics"},{"domain":"xlvi.academy","status":"available","attractiveness":56,"demand":3,"length":4,"created":"","expires":"","registrar":null,"sectors":"Mathematics"},{"domain":"xxvii.academy","status":"available","attractiveness":56,"demand":3,"length":5,"created":"","expires":"","registrar":null,"sectors":"Mathematics"},{"domain":"xlvii.academy","status":"available","attractiveness":56,"demand":2,"length":5,"created":"","expires":"","registrar":null,"sectors":"Mathematics"},{"domain":"xxxi.academy","status":"available","attractiveness":56,"demand":9,"length":4,"created":"","expires":"","registrar":null,"sectors":"Mathematics"},{"domain":"xxxiii.academy","status":"available","attractiveness":56,"demand":2,"length":6,"created":"","expires":"","registrar":null,"sectors":"Mathematics"},{"domain":"xliv.academy","status":"available","attractiveness":56,"demand":2,"length":4,"created":"","expires":"","registrar":null,"sectors":"Mathematics"},{"domain":"xxxvii.academy","status":"available","attractiveness":56,"demand":2,"length":6,"created":"","expires":"","registrar":null,"sectors":"Mathematics"},{"domain":"fiftynine.academy","status":"available","attractiveness":56,"demand":4,"length":10,"created":"","expires":"","registrar":null,"sectors":"Mathematics"},{"domain":"xlv.academy","status":"available","attractiveness":56,"demand":6,"length":3,"created":"","expires":"","registrar":null,"sectors":"Mathematics"},{"domain":"fortynine.academy","status":"available","attractiveness":56,"demand":3,"length":10,"created":"","expires":"","registrar":null,"sectors":"Mathematics"},{"domain":"lvi.academy","status":"available","attractiveness":56,"demand":8,"length":3,"created":"","expires":"","registrar":null,"sectors":"Mathematics"},{"domain":"viii.academy","status":"available","attractiveness":54,"demand":6,"length":4,"created":"","expires":"","registrar":null,"sectors":"Mathematics"},{"domain":"deuceace.academy","status":"available","attractiveness":54,"demand":2,"length":9,"created":"","expires":"","registrar":null,"sectors":"Sports"},{"domain":"abient.academy","status":"available","attractiveness":54,"demand":1,"length":6,"created":"","expires":"","registrar":null,"sectors":"Science"},{"domain":"quaternity.academy","status":"available","attractiveness":54,"demand":4,"length":10,"created":"","expires":"","registrar":null,"sectors":"Mathematics"},{"domain":"quatern.academy","status":"available","attractiveness":54,"demand":2,"length":7,"created":"","expires":"","registrar":null,"sectors":"Mathematics"},{"domain":"abatic.academy","status":"available","attractiveness":54,"demand":1,"length":6,"created":"","expires":"","registrar":null,"sectors":"Science"},{"domain":"twoscore.academy","status":"available","attractiveness":54,"demand":2,"length":8,"created":"","expires":"","registrar":null,"sectors":"Mathematics"},{"domain":"topnotch.academy","status":"available","attractiveness":54,"demand":18,"length":8,"created":"","expires":"","registrar":null,"sectors":"Business"},{"domain":"threescore.academy","status":"available","attractiveness":54,"demand":1,"length":10,"created":"","expires":"","registrar":null,"sectors":"Mathematics"},{"domain":"quaternion.academy","status":"available","attractiveness":54,"demand":6,"length":10,"created":"","expires":"","registrar":null,"sectors":"Mathematics"},{"domain":"abatable.academy","status":"available","attractiveness":54,"demand":1,"length":8,"created":"","expires":"","registrar":null,"sectors":"Law"},{"domain":"aboral.academy","status":"available","attractiveness":54,"demand":2,"length":6,"created":"","expires":"","registrar":null,"sectors":"Science"},{"domain":"fortyfive.academy","status":"available","attractiveness":54,"demand":4,"length":10,"created":"","expires":"","registrar":null,"sectors":"Mathematics"},{"domain":"abaxial.academy","status":"available","attractiveness":54,"demand":1,"length":7,"created":"","expires":"","registrar":null,"sectors":"Science"},{"domain":"abasic.academy","status":"available","attractiveness":54,"demand":1,"length":6,"created":"","expires":"","registrar":null,"sectors":"Science"},{"domain":"scratchy.academy","status":"available","attractiveness":54,"demand":3,"length":8,"created":"","expires":"","registrar":null,"sectors":"Fashion"},{"domain":"abducens.academy","status":"available","attractiveness":54,"demand":1,"length":8,"created":"","expires":"","registrar":null,"sectors":"Medicine"},{"domain":"lxi.academy","status":"available","attractiveness":52,"demand":5,"length":3,"created":"","expires":"","registrar":null,"sectors":"Mathematics"},{"domain":"xciv.academy","status":"available","attractiveness":52,"demand":2,"length":4,"created":"","expires":"","registrar":null,"sectors":"Mathematics"},{"domain":"sixtysix.academy","status":"available","attractiveness":52,"demand":4,"length":9,"created":"","expires":"","registrar":null,"sectors":"Mathematics"},{"domain":"lxviii.academy","status":"available","attractiveness":52,"demand":1,"length":6,"created":"","expires":"","registrar":null,"sectors":"Mathematics"},{"domain":"abstruse.academy","status":"available","attractiveness":52,"demand":5,"length":8,"created":"","expires":"","registrar":null,"sectors":"Humanities,Mathematics,Science"},{"domain":"lxxi.academy","status":"available","attractiveness":52,"demand":1,"length":4,"created":"","expires":"","registrar":null,"sectors":"Mathematics"},{"domain":"lxxxvii.academy","status":"available","attractiveness":52,"demand":1,"length":7,"created":"","expires":"","registrar":null,"sectors":"Mathematics"},{"domain":"lxxiv.academy","status":"available","attractiveness":52,"demand":1,"length":5,"created":"","expires":"","registrar":null,"sectors":"Mathematics"},{"domain":"ninetysix.academy","status":"available","attractiveness":52,"demand":4,"length":10,"created":"","expires":"","registrar":null,"sectors":"Mathematics"},{"domain":"lxxii.academy","status":"available","attractiveness":52,"demand":1,"length":5,"created":"","expires":"","registrar":null,"sectors":"Mathematics"},{"domain":"lxii.academy","status":"available","attractiveness":52,"demand":1,"length":4,"created":"","expires":"","registrar":null,"sectors":"Mathematics"},{"domain":"aboulic.academy","status":"available","attractiveness":52,"demand":1,"length":7,"created":"","expires":"","registrar":null,"sectors":"Medicine"},{"domain":"ninetyone.academy","status":"available","attractiveness":52,"demand":5,"length":10,"created":"","expires":"","registrar":null,"sectors":"Mathematics"},{"domain":"xcvii.academy","status":"available","attractiveness":52,"demand":1,"length":5,"created":"","expires":"","registrar":null,"sectors":"Mathematics"},{"domain":"eightytwo.academy","status":"available","attractiveness":52,"demand":4,"length":10,"created":"","expires":"","registrar":null,"sectors":"Mathematics"},{"domain":"eightyone.academy","status":"available","attractiveness":52,"demand":3,"length":10,"created":"","expires":"","registrar":null,"sectors":"Mathematics"},{"domain":"lxv.academy","status":"available","attractiveness":52,"demand":5,"length":3,"created":"","expires":"","registrar":null,"sectors":"Mathematics"},{"domain":"lxxxiv.academy","status":"available","attractiveness":52,"demand":1,"length":6,"created":"","expires":"","registrar":null,"sectors":"Mathematics"},{"domain":"lxxxii.academy","status":"available","attractiveness":52,"demand":1,"length":6,"created":"","expires":"","registrar":null,"sectors":"Mathematics"},{"domain":"lxxxv.academy","status":"available","attractiveness":52,"demand":1,"length":5,"created":"","expires":"","registrar":null,"sectors":"Mathematics"},{"domain":"lxvii.academy","status":"available","attractiveness":52,"demand":1,"length":5,"created":"","expires":"","registrar":null,"sectors":"Mathematics"},{"domain":"ninetytwo.academy","status":"available","attractiveness":52,"demand":4,"length":10,"created":"","expires":"","registrar":null,"sectors":"Mathematics"},{"domain":"lxiv.academy","status":"available","attractiveness":52,"demand":3,"length":4,"created":"","expires":"","registrar":null,"sectors":"Mathematics"},{"domain":"lxiii.academy","status":"available","attractiveness":52,"demand":2,"length":5,"created":"","expires":"","registrar":null,"sectors":"Mathematics"},{"domain":"chagrined.academy","status":"available","attractiveness":52,"demand":1,"length":9,"created":"","expires":"","registrar":null,"sectors":"Humanities"},{"domain":"ablated.academy","status":"available","attractiveness":52,"demand":1,"length":7,"created":"","expires":"","registrar":null,"sectors":"Science"},{"domain":"lxvi.academy","status":"available","attractiveness":52,"demand":3,"length":4,"created":"","expires":"","registrar":null,"sectors":"Mathematics"},{"domain":"lxxxvi.academy","status":"available","attractiveness":52,"demand":1,"length":6,"created":"","expires":"","registrar":null,"sectors":"Mathematics"},{"domain":"xcii.academy","status":"available","attractiveness":52,"demand":2,"length":4,"created":"","expires":"","registrar":null,"sectors":"Mathematics"},{"domain":"sixtytwo.academy","status":"available","attractiveness":52,"demand":3,"length":9,"created":"","expires":"","registrar":null,"sectors":"Mathematics"},{"domain":"lxxv.academy","status":"available","attractiveness":52,"demand":1,"length":4,"created":"","expires":"","registrar":null,"sectors":"Mathematics"},{"domain":"sixtyfive.academy","status":"available","attractiveness":52,"demand":3,"length":10,"created":"","expires":"","registrar":null,"sectors":"Mathematics"},{"domain":"lxxvi.academy","status":"available","attractiveness":52,"demand":1,"length":5,"created":"","expires":"","registrar":null,"sectors":"Mathematics"},{"domain":"lxxxiii.academy","status":"available","attractiveness":52,"demand":1,"length":7,"created":"","expires":"","registrar":null,"sectors":"Mathematics"},{"domain":"sixtyfour.academy","status":"available","attractiveness":52,"demand":3,"length":10,"created":"","expires":"","registrar":null,"sectors":"Mathematics"},{"domain":"lxxvii.academy","status":"available","attractiveness":52,"demand":2,"length":6,"created":"","expires":"","registrar":null,"sectors":"Mathematics"},{"domain":"xciii.academy","status":"available","attractiveness":52,"demand":1,"length":5,"created":"","expires":"","registrar":null,"sectors":"Mathematics"},{"domain":"xcvi.academy","status":"available","attractiveness":52,"demand":2,"length":4,"created":"","expires":"","registrar":null,"sectors":"Mathematics"},{"domain":"ixc.academy","status":"available","attractiveness":52,"demand":5,"length":3,"created":"","expires":"","registrar":null,"sectors":"Mathematics"},{"domain":"xcv.academy","status":"available","attractiveness":52,"demand":7,"length":3,"created":"","expires":"","registrar":null,"sectors":"Mathematics"},{"domain":"ixl.academy","status":"available","attractiveness":52,"demand":9,"length":3,"created":"","expires":"","registrar":null,"sectors":"Mathematics"},{"domain":"lxxxi.academy","status":"available","attractiveness":52,"demand":1,"length":5,"created":"","expires":"","registrar":null,"sectors":"Mathematics"},{"domain":"xci.academy","status":"available","attractiveness":52,"demand":4,"length":3,"created":"","expires":"","registrar":null,"sectors":"Mathematics"},{"domain":"lxxiii.academy","status":"available","attractiveness":52,"demand":1,"length":6,"created":"","expires":"","registrar":null,"sectors":"Mathematics"},{"domain":"xcviii.academy","status":"available","attractiveness":52,"demand":1,"length":6,"created":"","expires":"","registrar":null,"sectors":"Mathematics"},{"domain":"abducting.academy","status":"available","attractiveness":50,"demand":0,"length":9,"created":"","expires":"","registrar":null,"sectors":"Medicine"},{"domain":"lxx.academy","status":"available","attractiveness":50,"demand":5,"length":3,"created":"","expires":"","registrar":null,"sectors":"Mathematics"},{"domain":"abactinal.academy","status":"available","attractiveness":50,"demand":0,"length":9,"created":"","expires":"","registrar":null,"sectors":"Science"},{"domain":"abbatial.academy","status":"available","attractiveness":50,"demand":0,"length":8,"created":"","expires":"","registrar":null,"sectors":"Religion"},{"domain":"abranchial.academy","status":"available","attractiveness":50,"demand":0,"length":10,"created":"","expires":"","registrar":null,"sectors":"Science"},{"domain":"triplet.academy","status":"available","attractiveness":50,"demand":8,"length":7,"created":"","expires":"","registrar":null,"sectors":"Science"},{"domain":"abdicable.academy","status":"available","attractiveness":50,"demand":0,"length":9,"created":"","expires":"","registrar":null,"sectors":"Law"},{"domain":"ogdoad.academy","status":"available","attractiveness":50,"demand":1,"length":6,"created":"","expires":"","registrar":null,"sectors":"Mathematics"},{"domain":"gillless.academy","status":"available","attractiveness":50,"demand":0,"length":9,"created":"","expires":"","registrar":null,"sectors":"Science"},{"domain":"abomasal.academy","status":"available","attractiveness":50,"demand":0,"length":8,"created":"","expires":"","registrar":null,"sectors":"Agriculture"},{"domain":"broached.academy","status":"available","attractiveness":50,"demand":0,"length":8,"created":"","expires":"","registrar":null,"sectors":"Food and Beverage"},{"domain":"cinque.academy","status":"available","attractiveness":50,"demand":7,"length":6,"created":"","expires":"","registrar":null,"sectors":"Mathematics"},{"domain":"lxxxviii.academy","status":"available","attractiveness":48,"demand":1,"length":8,"created":"","expires":"","registrar":null,"sectors":"Mathematics"},{"domain":"apriori.academy","status":"available","attractiveness":48,"demand":13,"length":8,"created":"","expires":"","registrar":null,"sectors":"Mathematics"},{"domain":"quaternary.academy","status":"available","attractiveness":46,"demand":3,"length":10,"created":"","expires":"","registrar":null,"sectors":"Mathematics"}]